uipath_connectors/microsoft_azure/__init__.py
uipath_connectors/microsoft_azure/client.py
uipath_connectors/microsoft_azure/errors.py
uipath_connectors/microsoft_azure/py.typed
uipath_connectors/microsoft_azure/types.py
uipath_connectors/microsoft_azure/api/__init__.py
uipath_connectors/microsoft_azure/api/alerts/__init__.py
uipath_connectors/microsoft_azure/api/alerts/list_security_alerts.py
uipath_connectors/microsoft_azure/api/application_groupresourcegroups/__init__.py
uipath_connectors/microsoft_azure/api/application_groupresourcegroups/assign_user_to_application_group.py
uipath_connectors/microsoft_azure/api/assignment_idresource_groupsapplication_groups/__init__.py
uipath_connectors/microsoft_azure/api/assignment_idresource_groupsapplication_groups/delete_assignment_id.py
uipath_connectors/microsoft_azure/api/assignment_idresource_groupsapplication_groups/get_assignment_id.py
uipath_connectors/microsoft_azure/api/host_poolsresource_groups/__init__.py
uipath_connectors/microsoft_azure/api/host_poolsresource_groups/get_registration_token_for_hostpool.py
uipath_connectors/microsoft_azure/api/hostpoolresource_groups/__init__.py
uipath_connectors/microsoft_azure/api/hostpoolresource_groups/create_host_pool.py
uipath_connectors/microsoft_azure/api/hostpoolresource_groups/delete_host_pool.py
uipath_connectors/microsoft_azure/api/hostpoolresource_groups/get_host_pool.py
uipath_connectors/microsoft_azure/api/hostpoolresource_groups/list_host_pool.py
uipath_connectors/microsoft_azure/api/hostpoolresource_groups/update_host_pool.py
uipath_connectors/microsoft_azure/api/locationsalerts/__init__.py
uipath_connectors/microsoft_azure/api/locationsalerts/get_security_alert.py
uipath_connectors/microsoft_azure/api/locationsalertsnew_state/__init__.py
uipath_connectors/microsoft_azure/api/locationsalertsnew_state/set_security_alert_state.py
uipath_connectors/microsoft_azure/api/network_interfaces/__init__.py
uipath_connectors_microsoft_azure-1.16.5.dev12.dist-info/METADATA
uipath_connectors_microsoft_azure-1.16.5.dev12.dist-info/WHEEL
uipath_connectors_microsoft_azure-1.16.5.dev12.dist-info/entry_points.txt
uipath_connectors_microsoft_azure-1.16.5.dev12.dist-info/top_level.txt
uipath_connectors_microsoft_azure-1.16.5.dev12.dist-info/RECORD
